piplock.py
piplock-0.1.0.dist-info/DESCRIPTION.rst
piplock-0.1.0.dist-info/METADATA
piplock-0.1.0.dist-info/RECORD
piplock-0.1.0.dist-info/WHEEL
piplock-0.1.0.dist-info/entry_points.txt
piplock-0.1.0.dist-info/metadata.json
piplock-0.1.0.dist-info/top_level.txt
