Metadata-Version: 2.0
Name: piplock
Version: 0.1.0
Summary: pip requirements For Aliens
Home-page: https://github.com/hirokiky/piplock
Author: Hiroki Kiyohara
Author-email: hirokiky@gmail.com
License: UNKNOWN
Platform: UNKNOWN
